pytest_dpg/__init__.py
pytest_dpg/commands.py
pytest_dpg/dpg_helpers.py
pytest_dpg/invoker.py
pytest_dpg/plugin.py
pytest_dpg/receiver.py
pytest_dpg-0.1.5.dist-info/METADATA
pytest_dpg-0.1.5.dist-info/WHEEL
pytest_dpg-0.1.5.dist-info/entry_points.txt
pytest_dpg-0.1.5.dist-info/RECORD
