Metadata-Version: 2.3
Name: pytest-dpg
Version: 0.1.5
Summary: pytest-dpg is a pytest plugin for testing Dear PyGui (DPG) applications
Project-URL: repository, https://github.com/tbruno25/pytest-dpg
Author-email: TJ <tbruno25@gmail.com>
Keywords: dearpygui,dpg
Classifier: Framework :: Pytest
Classifier: Intended Audience :: Developers
Classifier: License :: OSI Approved :: GNU General Public License v3 (GPLv3)
Classifier: Operating System :: OS Independent
Classifier: Programming Language :: Python :: 3
Classifier: Programming Language :: Python :: 3.10
Classifier: Programming Language :: Python :: 3.11
Classifier: Programming Language :: Python :: 3.12
Classifier: Topic :: Software Development :: Quality Assurance
Classifier: Topic :: Software Development :: Testing
Classifier: Topic :: Software Development :: User Interfaces
Classifier: Topic :: Utilities
Requires-Python: >=3.10
Requires-Dist: dearpygui>=1.11.1
Requires-Dist: multiprocess>=0.70.16
Requires-Dist: pyautogui>=0.9.54
